ml3_platform_sdk/__init__.py
ml3_platform_sdk/client.py
ml3_platform_sdk/enums.py
ml3_platform_sdk/exceptions.py
ml3_platform_sdk/models.py
ml3_platform_sdk/py.typed
ml3_platform_sdk/utils.py
ml3_platform_sdk/core/__init__.py
ml3_platform_sdk/core/client_impl.py
ml3_platform_sdk/core/connection.py
ml3_platform_sdk/core/enums.py
ml3_platform_sdk/core/models.py
ml3_platform_sdk/core/requests.py
ml3_platform_sdk/core/responses.py
ml3_platform_sdk/core/singleton.py
scripts/update_mkgendocs.py
scripts/update_version.py
tests/__init__.py
tests/test_client_initialization.py
tests/test_placeholder.py
ml3_platform_sdk-0.0.36.dist-info/METADATA
ml3_platform_sdk-0.0.36.dist-info/WHEEL
ml3_platform_sdk-0.0.36.dist-info/top_level.txt
ml3_platform_sdk-0.0.36.dist-info/RECORD
